{"css": "base1.css", "legend": "Player Details", "HTML_fields": [{"tag": "input", "type": "text", "class": "form-control", "label": "Name of Song", "id": "name_of_song", "name": "name_of_song", "required": "true"}, {"tag": "input", "type": "text", "class": "form-control", "label": "Artist", "id": "artist", "name": "artist", "required": "true"}, {"tag": "input", "type": "text", "class": "form-control", "label": "Genre", "id": "genre", "name": "genre", "required": "true"}, {"tag": "input", "type": "number", "class": "form-control", "label": "Year of Release", "id": "year_of_release", "name": "year_of_release", "required": "true"}, {"tag": "input", "type": "file", "class": "form-control", "label": "Upload", "id": "upload", "name": "upload", "required": "true"}, {"tag": "input", "type": "checkbox", "class": "form-control", "label": "Favorite", "id": "favorite", "name": "favorite", "label1": {"A": "A1"}, "required": "true"}, {"tag": "button", "type": "submit", "class": "form-control", "label": "Submit", "id": "submit", "name": "submit"}], "HTML_table": {"headers": ["Name of Song", "Artist", "Genre", "Year of Release", "Upload", "Favorite"], "values": [{"name": "name_of_song", "type": "text"}, {"name": "artist", "type": "text"}, {"name": "genre", "type": "text"}, {"name": "year_of_release", "type": "text"}, {"name": "upload", "type": "file"}, {"name": "favorite", "type": "text"}, {"name": "name_of_song", "type": "text"}, {"name": "artist", "type": "text"}, {"name": "genre", "type": "text"}, {"name": "year_of_release", "type": "text"}, {"name": "upload", "type": "file"}, {"name": "favorite", "type": "text"}], "searchable_fields": ["name_of_song", "artist", "genre", "year_of_release", "upload", "favorite"]}, "Model_fields": {"tableName": "Songs", "tableFields": [{"type": "CharField", "name": "name_of_song", "isBlank": "True", "isNull": "True", "maxLength": "100"}, {"type": "CharField", "name": "artist", "isBlank": "True", "isNull": "True", "maxLength": "100"}, {"type": "CharField", "name": "genre", "isBlank": "True", "isNull": "True", "maxLength": "100"}, {"type": "IntegerField", "name": "year_of_release", "isBlank": "True", "isNull": "True", "default": "100"}, {"type": "FileField", "name": "upload", "isBlank": "True", "isNull": "True", "filePath": "MusicDetails_attachment"}, {"type": "BooleanField", "name": "favorite", "isBlank": "True", "isNull": "True", "default": "0"}]}}